setup.py
TracHierWiki.egg-info/PKG-INFO
TracHierWiki.egg-info/SOURCES.txt
TracHierWiki.egg-info/dependency_links.txt
TracHierWiki.egg-info/entry_points.txt
TracHierWiki.egg-info/top_level.txt
hierwiki/__init__.py
hierwiki/filter.py
hierwiki/formatter.py
hierwiki/macros/__init__.py
hierwiki/macros/parentwiki.py
hierwiki/macros/subwiki.py
