Metadata-Version: 1.0
Name: TracHierWiki
Version: 1.0
Summary: Hierarchical wiki utilities for Trac.
Home-page: http://trac-hacks.org/wiki/HierWikiPlugin
Author: Noah Kantrowitz
Author-email: coderanger@yahoo.com
License: BSD
Keywords: trac plugin macros wiki hierarchy
Platform: UNKNOWN
Classifier: Framework :: Trac
